MANIFEST.in
README.md
setup.py
graphene_mongoengine/__init__.py
graphene_mongoengine/converter.py
graphene_mongoengine/fields.py
graphene_mongoengine/registry.py
graphene_mongoengine/types.py
graphene_mongoengine/utils.py
graphene_mongoengine.egg-info/PKG-INFO
graphene_mongoengine.egg-info/SOURCES.txt
graphene_mongoengine.egg-info/dependency_links.txt
graphene_mongoengine.egg-info/not-zip-safe
graphene_mongoengine.egg-info/requires.txt
graphene_mongoengine.egg-info/top_level.txt