Metadata-Version: 1.0
Name: graphene-mongoengine
Version: 0.1
Summary: Adding graphene support for mongoengine Models, inspired in Django
Home-page: https://github.com/tomasgarzon/graphene-mongoengine
Author: Tomas Garzon
Author-email: tomasgarzonhervas@gmail.com
License: MIT
Platform: UNKNOWN
